ddbimp/__init__.py
ddbimp/cli.py
ddbimp/importer.py
ddbimp-0.4.dist-info/LICENSE
ddbimp-0.4.dist-info/METADATA
ddbimp-0.4.dist-info/WHEEL
ddbimp-0.4.dist-info/entry_points.txt
ddbimp-0.4.dist-info/top_level.txt
ddbimp-0.4.dist-info/RECORD
