Metadata-Version: 2.1
Name: ddbimp
Version: 0.4
Summary: Easily load data from CSV to test out your DynamoDB table design
Home-page: https://github.com/AlexJReid/dynamodb-dev-importer
Author: AlexJReid
Author-email: alexjreid@me.com
License: Apache
Platform: UNKNOWN
Requires-Dist: boto3
